tps_dashboard_utils/__init__.py
tps_dashboard_utils/colours/__init__.py
tps_dashboard_utils/colours/categorical.py
tps_dashboard_utils/colours/colour_names.py
tps_dashboard_utils/dashboard/__init__.py
tps_dashboard_utils/dashboard/charts.py
tps_dashboard_utils/dashboard/layout.py
tps_dashboard_utils/data_functions/__init__.py
tps_dashboard_utils/data_functions/data.py
tps_dashboard_utils/data_functions/github.py
tps_dashboard_utils/date_functions/__init__.py
tps_dashboard_utils/date_functions/monthly.py
tps_dashboard_utils/date_functions/quarterly.py
tps_dashboard_utils/date_functions/six_monthly.py
tps_dashboard_utils/date_functions/weekly.py
tps_dashboard_utils/date_functions/yearly.py
tps_dashboard_utils-0.0.34.dist-info/LICENSE
tps_dashboard_utils-0.0.34.dist-info/METADATA
tps_dashboard_utils-0.0.34.dist-info/WHEEL
tps_dashboard_utils-0.0.34.dist-info/top_level.txt
tps_dashboard_utils-0.0.34.dist-info/RECORD
