Metadata-Version: 2.1
Name: tps-dashboard-utils
Version: 0.0.34
Summary: Some useful utilities for building dashboards
Home-page: https://github.com/losthippo/tps-dashboard-utils
Author: Lisa Hendry
Author-email: lisahendry@turningpointscotland.com
Classifier: Programming Language :: Python :: 3
Classifier: License :: OSI Approved :: MIT License
Classifier: Operating System :: OS Independent
Requires-Python: >=3.6
License-File: LICENSE
